LICENSE.txt
README.md
setup.py
EXIFnaming/__init__.py
EXIFnaming/deprecated_exif.py
EXIFnaming/futureexif.py
EXIFnaming/nameop.py
EXIFnaming/picture.py
EXIFnaming/placeinfo.py
EXIFnaming/readexif.py
EXIFnaming/setexif.py
EXIFnaming/steps.py
EXIFnaming.egg-info/PKG-INFO
EXIFnaming.egg-info/SOURCES.txt
EXIFnaming.egg-info/dependency_links.txt
EXIFnaming.egg-info/requires.txt
EXIFnaming.egg-info/top_level.txt
EXIFnaming/helpers/__init__.py
EXIFnaming/helpers/constants.py
EXIFnaming/helpers/cv2op.py
EXIFnaming/helpers/date.py
EXIFnaming/helpers/decode.py
EXIFnaming/helpers/fileop.py
EXIFnaming/helpers/measuring_tools.py
EXIFnaming/helpers/misc.py
EXIFnaming/helpers/program_dir.py
EXIFnaming/helpers/settings.py
EXIFnaming/helpers/tag_conversion.py
EXIFnaming/helpers/tags.py
EXIFnaming/models/DMC_TZ101.py
EXIFnaming/models/DMC_TZ7.py
EXIFnaming/models/ModelBase.py
EXIFnaming/models/NormalFile.py
EXIFnaming/models/PhotoFile.py
EXIFnaming/models/__init__.py
tests/__init__.py
tests/test_first.py
tests/test_tag_conversion.py