Metadata-Version: 2.1
Name: EXIFnaming
Version: 0.0.21
Summary: Tools for organizing and tagging photos
Home-page: https://github.com/mvolkert/EXIFnaming
Author: Marco Volkert
Author-email: marco.volkert24@gmx.de
License: MIT License
Keywords: exif exiftool photo tagging geotagging renaming photo-mode ordering python lumix panasonic camera digital-camera photos camera-model TZ101 organizing
Platform: UNKNOWN
Classifier: Programming Language :: Python :: 3
Classifier: Programming Language :: Python :: 3.7
Classifier: Development Status :: 3 - Alpha
Classifier: Topic :: Multimedia :: Graphics :: Capture :: Digital Camera
Classifier: Topic :: Utilities
Classifier: Intended Audience :: Developers
Classifier: Intended Audience :: Other Audience
Classifier: License :: OSI Approved :: MIT License
Classifier: Operating System :: OS Independent
Classifier: Operating System :: Microsoft :: Windows :: Windows 10
Classifier: Natural Language :: English
Classifier: Natural Language :: German
Classifier: Typing :: Typed
Requires-Python: >=3.6
License-File: LICENSE.txt
